Metadata-Version: 2.1
Name: modelwithlog
Version: 0.1
Summary: Django model with log
Home-page: https://gitlab.com/kas-factory/packages/django-model-with-log
Author: Aurora @ KF
Author-email: aurora@kasfactory.net
License: COPYRIGHT
Platform: UNKNOWN
